pydkit/__init__.py
pydkit/base.py
pydkit/csv.py
pydkit/json.py
pydkit/timezones.py
pydkit/types.py
pydkit-0.0.2.dist-info/LICENSE
pydkit-0.0.2.dist-info/METADATA
pydkit-0.0.2.dist-info/WHEEL
pydkit-0.0.2.dist-info/RECORD
