Metadata-Version: 2.1
Name: pydkit
Version: 0.0.2
Summary: Extended kit and tools for pydantic, to enjoy pydantic even more!
Home-page: https://github.com/manimozaffar/pydkit
Author: Mani Mozaffar
Author-email: fmani.mozaffar@gmail.com
Requires-Python: >=3.8,<4.0
Classifier: Programming Language :: Python :: 3
Classifier: Programming Language :: Python :: 3.8
Classifier: Programming Language :: Python :: 3.9
Classifier: Programming Language :: Python :: 3.10
Classifier: Programming Language :: Python :: 3.11
Classifier: Programming Language :: Python :: 3.12
Requires-Dist: aiofiles (>=23.2.1,<24.0.0)
Requires-Dist: asyncer (>=0.0.2,<0.0.3)
Requires-Dist: pydantic (>=2.5.2,<3.0.0)
Requires-Dist: pytest-asyncio (>=0.21.1,<0.22.0)
Project-URL: Documentation, https://manimozaffar.github.io/pydkit/
Project-URL: Repository, https://github.com/manimozaffar/pydkit
